pyodide_backend/__init__.py
pyodide_backend/custom_print.py
pyodide_backend/display_hook.py
pyodide_backend/exercise.py
pyodide_backend/interactive_shell.py
pyodide_backend/matplotlib_custom_backend.py
pyodide_backend/matplotlib_plots.py
pyodide_backend/process.py
pyodide_backend/task.py
pyodide_backend/version.py
pyodide_backend-1.6.6.dist-info/METADATA
pyodide_backend-1.6.6.dist-info/WHEEL
pyodide_backend-1.6.6.dist-info/top_level.txt
pyodide_backend-1.6.6.dist-info/RECORD
