Metadata-Version: 2.4
Name: pyodide_backend
Version: 1.6.6
Requires-Python: >=3.12
Requires-Dist: pythonwhat~=2.29.0
Provides-Extra: build
Requires-Dist: setuptools~=74.1.2; extra == "build"
Requires-Dist: build~=1.2.2; extra == "build"
Provides-Extra: test
Requires-Dist: pytest~=8.3.3; extra == "test"
Requires-Dist: black~=24.8.0; extra == "test"
Requires-Dist: numpy==2.0.2; extra == "test"
Requires-Dist: matplotlib==3.8.4; extra == "test"
Requires-Dist: pytest-snapshot~=0.9.0; extra == "test"
